flask_inject.py
Flask_Inject-1.1.0.dist-info/DESCRIPTION.rst
Flask_Inject-1.1.0.dist-info/METADATA
Flask_Inject-1.1.0.dist-info/metadata.json
Flask_Inject-1.1.0.dist-info/RECORD
Flask_Inject-1.1.0.dist-info/top_level.txt
Flask_Inject-1.1.0.dist-info/WHEEL
