Metadata-Version: 2.0
Name: Flask-Inject
Version: 1.1.0
Summary: A micro dependency injection framework for Flask micro web framework :)
Home-page: https://github.com/imwithye/flask-inject
Author: Ciel
Author-email: imwithye@gmail.com
License: BSD
Platform: any
Classifier: Environment :: Web Environment
Classifier: Intended Audience :: Developers
Classifier: License :: OSI Approved :: BSD License
Classifier: Operating System :: OS Independent
Classifier: Programming Language :: Python
Classifier: Topic :: Internet :: WWW/HTTP :: Dynamic Content
Classifier: Topic :: Software Development :: Libraries :: Python Modules
Requires-Dist: Flask
